README.md
setup.py
Zgram/__init__.py
Zgram/__main__.py
Zgram/handler.py
Zgram/logger.py
Zgram/polling.py
Zgram/request.py
Zgram/schedule.py
Zgram/version.py
Zgram/webhook.py
Zgram/zgram.py
Zgram/plugins/__init__.py
Zgram/plugins/About/About.py
Zgram/plugins/About/__init__.py
Zgram/plugins/Chat/Chat.py
Zgram/plugins/Chat/__init__.py
Zgram/plugins/Hello/Hello.py
Zgram/plugins/Hello/__init__.py
Zgram/plugins/Menu/Menu.py
Zgram/plugins/Menu/__init__.py
Zgram/plugins/PluginCTL/PluginCTL.py
Zgram/plugins/PluginCTL/__init__.py
Zgram/plugins/Schedule/Schedule.py
Zgram/plugins/Schedule/__init__.py
Zgram/plugins/Uptime/Uptime.py
Zgram/plugins/Uptime/__init__.py
zgram.egg-info/PKG-INFO
zgram.egg-info/SOURCES.txt
zgram.egg-info/dependency_links.txt
zgram.egg-info/entry_points.txt
zgram.egg-info/requires.txt
zgram.egg-info/top_level.txt
zgram.egg-info/zip-safe