Metadata-Version: 2.1
Name: zgram
Version: 1.0.0
Summary: zgram is a robot framework based on Telegram Bot API, with plug-in system, easy to extend.
Home-page: https://ojoll.com
Author: Pluto
Author-email: hi@ojoll.com
License: GPLv3
Keywords: zgram telegram bot telegram bot api telegram
Platform: UNKNOWN
Classifier: Programming Language :: Python :: 3
Classifier: Operating System :: OS Independent
Classifier: License :: OSI Approved :: GNU General Public License v3 (GPLv3)
Requires-Python: >=3.7
